{
    "version": "0.17.3",
    "description": "Fast, pure Rust implementation of Beancount double-entry accounting",
    "homepage": "https://rustledger.github.io",
    "license": "GPL-3.0-only",
    "architecture": {
        "64bit": {
            "url": "https://github.com/rustledger/rustledger/releases/download/v0.17.3/rustledger-v0.17.3-x86_64-pc-windows-msvc.zip",
            "hash": "4522eaab906c9b4e455c339cb7fe30b8d6411b8e0a13a8a5354113bb15ad14e1"
        },
        "arm64": {
            "url": "https://github.com/rustledger/rustledger/releases/download/v0.17.3/rustledger-v0.17.3-aarch64-pc-windows-msvc.zip",
            "hash": "4daacc077e80228d29f05e019d205622c95b1e55850c29cc970e937896923e53"
        }
    },
    "bin": [
        "rledger.exe",
        "rledger-lsp.exe"
    ],
    "checkver": "github",
    "autoupdate": {
        "architecture": {
            "64bit": {
                "url": "https://github.com/rustledger/rustledger/releases/download/v$version/rustledger-v$version-x86_64-pc-windows-msvc.zip"
            },
            "arm64": {
                "url": "https://github.com/rustledger/rustledger/releases/download/v$version/rustledger-v$version-aarch64-pc-windows-msvc.zip"
            }
        }
    }
}
